{
  "relatedBlocks": [],
  "criticalRules": [
    "NEVER use spacingLeft - use spacing=10.0",
    "Preserve exact port styles from reference",
    "Copy parameter structures exactly"
  ],
  "description": "SUMMATION block",
  "anomalies": [
    "Non-standard height: 60.0",
    "dataLines=-1 indicates variable-size",
    "Special tag: Summation"
  ],
  "name": "SUMMATION",
  "commonUses": [],
  "sourceFile": "scilab-2026.0.1/scilab-2026.0.1/scilab/modules/scicos_blocks/macros/Linear/SUMMATION.sci"
}